shellfish/__about__.py
shellfish/__init__.py
shellfish/__main__.py
shellfish/_internal.py
shellfish/_pydantic.py
shellfish/_types.py
shellfish/aios/__init__.py
shellfish/aios/_path.py
shellfish/aioshutil.py
shellfish/batman.py
shellfish/const.py
shellfish/dev/__init__.py
shellfish/dev/popen_gen.py
shellfish/dev/run_async.py
shellfish/done.py
shellfish/dotenv.py
shellfish/echo.py
shellfish/exe.py
shellfish/fs/__init__.py
shellfish/fs/_async.py
shellfish/fs/promises.py
shellfish/libhash.py
shellfish/libsh/__init__.py
shellfish/libsh/_dirtree.py
shellfish/libsh/args.py
shellfish/osfs.py
shellfish/process.py
shellfish/psu.py
shellfish/py.typed
shellfish/sh.py
shellfish/sp.py
shellfish/stdio.py
shellfish/testing.py
shellfish/tests/__init__.py
shellfish/tests/test_fs.py
shellfish-0.7.1.dist-info/WHEEL
shellfish-0.7.1.dist-info/METADATA
shellfish-0.7.1.dist-info/RECORD
