Metadata-Version: 2.3
Name: shellfish
Version: 0.7.1
Summary: shellfish ~ shell & file-system utils
Keywords: dgpy,filesystem,fs,shell,typed
Author: jesse
Author-email: jesse <jesse@dgi.com>
Classifier: Development Status :: 5 - Production/Stable
Classifier: Intended Audience :: Developers
Classifier: License :: OSI Approved :: MIT License
Classifier: Programming Language :: Python
Classifier: Programming Language :: Python :: 3 :: Only
Classifier: Programming Language :: Python :: 3.11
Classifier: Programming Language :: Python :: 3.12
Classifier: Programming Language :: Python :: 3.13
Classifier: Programming Language :: Python :: 3.14
Classifier: Typing :: Typed
Requires-Dist: aiopen>=0.8
Requires-Dist: asyncify>=0.12
Requires-Dist: funkify>=0.7
Requires-Dist: jsonbourne>=0.32
Requires-Dist: listless>=0.4
Requires-Dist: pydantic>=2.0.3
Requires-Python: >=3.11, <4.0
